eclear/__init__.py
eclear/oauth2/__init__.py
eclear/oauth2/router.py
eclear.oauth2-0.0.1.dist-info/METADATA
eclear.oauth2-0.0.1.dist-info/WHEEL
eclear.oauth2-0.0.1.dist-info/top_level.txt
eclear.oauth2-0.0.1.dist-info/RECORD
