Metadata-Version: 2.1
Name: eclear.oauth2
Version: 0.0.1
Requires-Dist: fastapi ==0.101.0
Requires-Dist: pydantic >=2.1.1
Requires-Dist: aiohttp ==3.9.3
Requires-Dist: python-jose ==3.3.0
Requires-Dist: python-keycloak ==3.3.0
Requires-Dist: pydantic-settings
